{
    "version": "0.5",
    "railtrack_nodes": [
        [
            374.663086,
            132
        ],
        [
            1150.27002,
            634
        ],
        [
            199.27002,
            633
        ],
        [
            935.943848,
            81
        ],
        [
            1201.663086,
            348
        ],
        [
            654.933105,
            639
        ],
        [
            123.820801,
            350
        ]
    ],
    "buildings": [
        {
            "type": "farm",
            "position": [
                936,
                321
            ]
        },
        {
            "type": "farm",
            "position": [
                381,
                322
            ]
        },
        {
            "type": "farm",
            "position": [
                646,
                134
            ]
        },
        {
            "type": "area_51",
            "position": [
                654,
                478
            ]
        }
    ],
    "n_remaining_actions": 2,
    "texts": []
}